tgshg/__init__.py
tgshg/audio_process.py
tgshg/maya_commands.py
tgshg/maya_mesh_vertexs.py
tgshg/audio/__init__.py
tgshg/audio/audio_process.py
tgshg/audio/audiolazy/__init__.py
tgshg/audio/audiolazy/_internals.py
tgshg/audio/audiolazy/lazy_analysis.py
tgshg/audio/audiolazy/lazy_auditory.py
tgshg/audio/audiolazy/lazy_compat.py
tgshg/audio/audiolazy/lazy_core.py
tgshg/audio/audiolazy/lazy_filters.py
tgshg/audio/audiolazy/lazy_io.py
tgshg/audio/audiolazy/lazy_itertools.py
tgshg/audio/audiolazy/lazy_lpc.py
tgshg/audio/audiolazy/lazy_math.py
tgshg/audio/audiolazy/lazy_midi.py
tgshg/audio/audiolazy/lazy_misc.py
tgshg/audio/audiolazy/lazy_poly.py
tgshg/audio/audiolazy/lazy_stream.py
tgshg/audio/audiolazy/lazy_synth.py
tgshg/audio/audiolazy/lazy_text.py
tgshg/audio/audiolazy/lazy_wav.py
tgshg/dll/__init__.py
tgshg/dll/kalman.py
tgshg/maya_api/__init__.py
tgshg/maya_api/maya_commands.py
tgshg/maya_api/maya_mesh_vertexs.py
tgshg-1.0.1.dist-info/LICENSE
tgshg-1.0.1.dist-info/METADATA
tgshg-1.0.1.dist-info/WHEEL
tgshg-1.0.1.dist-info/top_level.txt
tgshg-1.0.1.dist-info/RECORD
