Metadata-Version: 2.1
Name: tgshg
Version: 1.0.1
Summary: A test small example package
Home-page: https://github.com/tgshg/pypi/tgshg
Author: tgshg
Author-email: tgshgworld@gmail.com
License: UNKNOWN
Platform: UNKNOWN
Classifier: Environment :: Plugins
Classifier: Intended Audience :: Developers
Classifier: License :: Free for non-commercial use
Classifier: Natural Language :: Chinese (Simplified)
Classifier: Operating System :: Microsoft :: Windows :: Windows 10
Classifier: Programming Language :: Python :: 2
Classifier: Topic :: Software Development :: Libraries :: Python Modules
